{
  "info": "",
  "sites": [
    { "domain": "xhamster.com", "visits": "208.75M" },
    { "domain": "qorno.com", "visits": "104.78M" },
    { "domain": "pornhub.com", "visits": "82.02M" },
    { "domain": "xhamster1.desi", "visits": "78.14M" },
    { "domain": "xvideos.com", "visits": "72.42M" },
    { "domain": "desitales2.com", "visits": "70.72M" },
    { "domain": "pornhat.com", "visits": "65.83M" },
    { "domain": "xhamster19.com", "visits": "61.46M" },
    { "domain": "iporntv.net", "visits": "57.95M" },
    { "domain": "xhaccess.com", "visits": "47.23M" },
    { "domain": "dinotube.com", "visits": "43.55M" },
    { "domain": "xnxx.com", "visits": "39.64M" },
    { "domain": "pussyspace.com", "visits": "32.01M" },
    { "domain": "spankbang.party", "visits": "30.56M" },
    { "domain": "desikahani2.net", "visits": "26.49M" },
    { "domain": "lobstertube.com", "visits": "24.19M" },
    { "domain": "hdtube.porn", "visits": "22.42M" },
    { "domain": "aznude.com", "visits": "22.2M" },
    { "domain": "xxx18hot.com", "visits": "21.62M" },
    { "domain": "hot-sex-tube.com", "visits": "21.36M" },
    { "domain": "xhamster2.com", "visits": "20.86M" },
    { "domain": "stripchat.global", "visits": "20.86M" },
    { "domain": "zbporn.tv", "visits": "20.67M" },
    { "domain": "fpo.xxx", "visits": "20.64M" },
    { "domain": "theporndude.com", "visits": "19.36M" },
    { "domain": "xhopen.com", "visits": "19.19M" },
    { "domain": "hdpornfree.xxx", "visits": "19.13M" },
    { "domain": "melonstube.com", "visits": "17.57M" },
    { "domain": "okxxx1.com", "visits": "17.55M" },
    { "domain": "hqporner.com", "visits": "17.24M" },
    { "domain": "xossipy.com", "visits": "16.83M" },
    { "domain": "freesexkahani.com", "visits": "16.63M" },
    { "domain": "pussyboy.net", "visits": "16.34M" },
    { "domain": "xxxindianstories.com", "visits": "16.12M" },
    { "domain": "totalfucktube.com", "visits": "15.93M" },
    { "domain": "aagmaal.com", "visits": "15.44M" },
    { "domain": "xhamster3.com", "visits": "15.08M" },
    { "domain": "pron.click", "visits": "14.75M" },
    { "domain": "thisvid.com", "visits": "14.24M" },
    { "domain": "bustybus.com", "visits": "14.15M" }
  ]
}
